[{"userProfilePK":5001914,"calendarDate":"2021-10-17","deviceId":3378489037,"timestamp":"2021-10-17T10:19:23.0","sport":"CYCLING","subSport":"GENERIC","weeklyTrainingLoadSum":0,"loadTunnelMin":722,"loadTunnelMax":1540,"trainingStatus":"DETRAINING","fitnessLevelTrend":"NO_CHANGE","loadLevelTrend":"DECREASING"},{"userProfilePK":5001914,"calendarDate":"2021-10-17","deviceId":3378489037,"timestamp":"2021-10-17T10:20:36.0","sport":"CYCLING","subSport":"GENERIC","weeklyTrainingLoadSum":587,"loadTunnelMin":722,"loadTunnelMax":1540,"trainingStatus":"UNPRODUCTIVE","fitnessLevelTrend":"DECREASING","loadLevelTrend":"DECREASING"},{"userProfilePK":5001914,"calendarDate":"2021-10-17","deviceId":3378489037,"timestamp":"2021-10-17T10:20:37.0","sport":"CYCLING","subSport":"GENERIC","weeklyTrainingLoadSum":1238,"loadTunnelMin":722,"loadTunnelMax":1540,"trainingStatus":"OVERREACHING","fitnessLevelTrend":"DECREASING","loadLevelTrend":"DECREASING"},{"userProfilePK":5001914,"calendarDate":"2021-10-17","deviceId":3378489037,"timestamp":"2021-10-17T17:42:56.0","sport":"CYCLING","subSport":"GENERIC","weeklyTrainingLoadSum":2034,"loadTunnelMin":722,"loadTunnelMax":1540,"trainingStatus":"OVERREACHING","fitnessLevelTrend":"DECREASING","loadLevelTrend":"NO_CHANGE"},{"userProfilePK":5001914,"calendarDate":"2021-10-17","deviceId":3378489037,"timestamp":"2021-10-17T17:42:57.0","sport":"CYCLING","subSport":"GENERIC","weeklyTrainingLoadSum":2034,"loadTunnelMin":722,"loadTunnelMax":1540,"trainingStatus":"OVERREACHING","fitnessLevelTrend":"DECREASING","loadLevelTrend":"NO_CHANGE"},{"userProfilePK":5001914,"calendarDate":"2021-10-17","deviceId":3378489037,"timestamp":"2021-10-18T06:00:00.0","sport":"CYCLING","subSport":"GENERIC","weeklyTrainingLoadSum":2034,"loadTunnelMin":722,"loadTunnelMax":1540,"trainingStatus":"OVERREACHING","fitnessLevelTrend":"DECREASING","loadLevelTrend":"NO_CHANGE"}]