[{"userProfilePK":5001914,"calendarDate":{"date":"Aug 4, 2021 12:00:00 AM"},"persistedTimestampGMT":{"date":"Aug 4, 2021 5:42:18 PM"},"timestampLocal":{"date":"Aug 4, 2021 4:48:38 AM"},"hydrationSource":"GARMIN_ACTIVITY","valueInML":0.0,"activityId":7246065155,"capped":false,"estimatedSweatLossInML":3602.0,"duration":22718.470703125},{"userProfilePK":5001914,"calendarDate":{"date":"Aug 10, 2021 12:00:00 AM"},"persistedTimestampGMT":{"date":"Aug 10, 2021 2:48:29 PM"},"timestampLocal":{"date":"Aug 10, 2021 5:15:34 AM"},"hydrationSource":"GARMIN_ACTIVITY","valueInML":0.0,"activityId":7279724884,"capped":false,"estimatedSweatLossInML":1976.0,"duration":12032.9248046875},{"userProfilePK":5001914,"calendarDate":{"date":"Aug 15, 2021 12:00:00 AM"},"persistedTimestampGMT":{"date":"Aug 15, 2021 8:49:21 PM"},"timestampLocal":{"date":"Aug 15, 2021 6:30:25 AM"},"hydrationSource":"GARMIN_ACTIVITY","valueInML":0.0,"activityId":7311555900,"capped":false,"estimatedSweatLossInML":6421.0,"duration":27664.626953125},{"userProfilePK":5001914,"calendarDate":{"date":"Aug 20, 2021 12:00:00 AM"},"persistedTimestampGMT":{"date":"Aug 20, 2021 3:00:58 PM"},"timestampLocal":{"date":"Aug 20, 2021 4:20:18 AM"},"hydrationSource":"GARMIN_ACTIVITY","valueInML":0.0,"activityId":7338468695,"capped":false,"estimatedSweatLossInML":2148.0,"duration":15548.4091796875},{"userProfilePK":5001914,"calendarDate":{"date":"Aug 22, 2021 12:00:00 AM"},"persistedTimestampGMT":{"date":"Aug 22, 2021 5:43:32 PM"},"timestampLocal":{"date":"Aug 22, 2021 3:35:03 AM"},"hydrationSource":"GARMIN_ACTIVITY","valueInML":0.0,"activityId":7351608264,"capped":false,"estimatedSweatLossInML":3939.0,"duration":27167.267578125},{"userProfilePK":5001914,"calendarDate":{"date":"Sep 5, 2021 12:00:00 AM"},"persistedTimestampGMT":{"date":"Sep 5, 2021 2:18:22 PM"},"timestampLocal":{"date":"Sep 5, 2021 4:12:52 AM"},"hydrationSource":"GARMIN_ACTIVITY","valueInML":0.0,"activityId":7432591193,"capped":false,"estimatedSweatLossInML":2114.0,"duration":13645.025390625},{"userProfilePK":5001914,"calendarDate":{"date":"Sep 6, 2021 12:00:00 AM"},"persistedTimestampGMT":{"date":"Sep 6, 2021 8:26:58 PM"},"timestampLocal":{"date":"Sep 6, 2021 3:17:25 AM"},"hydrationSource":"GARMIN_ACTIVITY","valueInML":0.0,"activityId":7440667690,"capped":false,"estimatedSweatLossInML":6013.0,"duration":36234.2421875},{"userProfilePK":5001914,"calendarDate":{"date":"Sep 18, 2021 12:00:00 AM"},"persistedTimestampGMT":{"date":"Sep 18, 2021 11:47:21 AM"},"timestampLocal":{"date":"Sep 18, 2021 5:22:15 AM"},"hydrationSource":"GARMIN_ACTIVITY","valueInML":0.0,"activityId":7510039647,"capped":false,"estimatedSweatLossInML":143.0,"duration":1448.0360107421875},{"userProfilePK":5001914,"calendarDate":{"date":"Sep 19, 2021 12:00:00 AM"},"persistedTimestampGMT":{"date":"Sep 19, 2021 3:56:07 PM"},"timestampLocal":{"date":"Sep 19, 2021 3:31:16 AM"},"hydrationSource":"GARMIN_ACTIVITY","valueInML":0.0,"activityId":7518125350,"capped":false,"estimatedSweatLossInML":3192.0,"duration":21507.634765625},{"userProfilePK":5001914,"calendarDate":{"date":"Sep 23, 2021 12:00:00 AM"},"persistedTimestampGMT":{"date":"Sep 23, 2021 2:09:33 PM"},"timestampLocal":{"date":"Sep 23, 2021 5:13:44 AM"},"hydrationSource":"GARMIN_ACTIVITY","valueInML":0.0,"activityId":7540082301,"capped":false,"estimatedSweatLossInML":1379.0,"duration":9888.986328125},{"userProfilePK":5001914,"calendarDate":{"date":"Sep 25, 2021 12:00:00 AM"},"persistedTimestampGMT":{"date":"Sep 25, 2021 4:09:41 PM"},"timestampLocal":{"date":"Sep 25, 2021 3:16:48 AM"},"hydrationSource":"GARMIN_ACTIVITY","valueInML":0.0,"activityId":7552210373,"capped":false,"estimatedSweatLossInML":2823.0,"duration":23003.73046875},{"userProfilePK":5001914,"calendarDate":{"date":"Sep 27, 2021 12:00:00 AM"},"persistedTimestampGMT":{"date":"Sep 27, 2021 2:09:47 PM"},"timestampLocal":{"date":"Sep 27, 2021 4:12:03 AM"},"hydrationSource":"GARMIN_ACTIVITY","valueInML":0.0,"activityId":7562936516,"capped":false,"estimatedSweatLossInML":1970.0,"duration":12528.037109375},{"userProfilePK":5001914,"calendarDate":{"date":"Oct 2, 2021 12:00:00 AM"},"persistedTimestampGMT":{"date":"Oct 2, 2021 7:30:01 PM"},"timestampLocal":{"date":"Oct 2, 2021 4:47:12 AM"},"hydrationSource":"GARMIN_ACTIVITY","valueInML":0.0,"activityId":7592240801,"capped":false,"estimatedSweatLossInML":3819.0,"duration":28746.490234375},{"userProfilePK":5001914,"calendarDate":{"date":"Oct 3, 2021 12:00:00 AM"},"persistedTimestampGMT":{"date":"Oct 3, 2021 4:23:26 PM"},"timestampLocal":{"date":"Oct 3, 2021 4:15:50 AM"},"hydrationSource":"GARMIN_ACTIVITY","valueInML":0.0,"activityId":7597290060,"capped":false,"estimatedSweatLossInML":2348.0,"duration":20198.83984375},{"userProfilePK":5001914,"calendarDate":{"date":"Oct 9, 2021 12:00:00 AM"},"persistedTimestampGMT":{"date":"Oct 9, 2021 6:14:12 PM"},"timestampLocal":{"date":"Oct 9, 2021 3:49:39 AM"},"hydrationSource":"GARMIN_ACTIVITY","valueInML":0.0,"activityId":7630427584,"capped":false,"estimatedSweatLossInML":3673.0,"duration":27978.25390625},{"userProfilePK":5001914,"calendarDate":{"date":"Oct 17, 2021 12:00:00 AM"},"persistedTimestampGMT":{"date":"Oct 17, 2021 5:44:13 PM"},"timestampLocal":{"date":"Oct 17, 2021 4:25:13 AM"},"hydrationSource":"GARMIN_ACTIVITY","valueInML":0.0,"activityId":7673936338,"capped":false,"estimatedSweatLossInML":2943.0,"duration":23998.908203125}]